CytofDR/__init__.py
CytofDR/__main__.py
CytofDR/dr.py
CytofDR/evaluation.py
CytofDR-0.3.1.dist-info/LICENSE.txt
CytofDR-0.3.1.dist-info/LICENSE_associated.txt
CytofDR-0.3.1.dist-info/METADATA
CytofDR-0.3.1.dist-info/WHEEL
CytofDR-0.3.1.dist-info/top_level.txt
CytofDR-0.3.1.dist-info/RECORD
