Metadata-Version: 2.1
Name: CytofDR
Version: 0.3.1
Summary: CyTOF Dimension Reduction Framework
Home-page: https://github.com/kevin931/CytofDR
Author: Kevin Wang
License: MIT
Platform: UNKNOWN
Classifier: License :: OSI Approved :: MIT License
Classifier: Programming Language :: Python :: 3 :: Only
Classifier: Natural Language :: English
Requires-Python: >=3.7
License-File: LICENSE.txt
License-File: LICENSE_associated.txt
Requires-Dist: scikit-learn
Requires-Dist: numpy
Requires-Dist: scipy
Requires-Dist: umap-learn
Requires-Dist: openTSNE
Requires-Dist: phate
Requires-Dist: annoy
Requires-Dist: matplotlib
Requires-Dist: seaborn
